psf_generator/__init__.py
psf_generator/propagators/__init__.py
psf_generator/propagators/cartesian_propagator.py
psf_generator/propagators/propagator.py
psf_generator/propagators/scalar_cartesian_propagator.py
psf_generator/propagators/scalar_spherical_propagator.py
psf_generator/propagators/spherical_propagator.py
psf_generator/propagators/vectorial_cartesian_propagator.py
psf_generator/propagators/vectorial_spherical_propagator.py
psf_generator/utils/__init__.py
psf_generator/utils/bessel.py
psf_generator/utils/czt.py
psf_generator/utils/handle_data.py
psf_generator/utils/integrate.py
psf_generator/utils/misc.py
psf_generator/utils/plots.py
psf_generator/utils/zernike.py
psf_generator-0.1.0.dist-info/licenses/LICENSE
psf_generator-0.1.0.dist-info/METADATA
psf_generator-0.1.0.dist-info/WHEEL
psf_generator-0.1.0.dist-info/top_level.txt
psf_generator-0.1.0.dist-info/RECORD
