Metadata-Version: 2.4
Name: psf-generator
Version: 0.1.0
Summary: PSF Generator: a PyTorch-based library to simulate point spread functions for microscopy.
Author-email: Yan Liu <yan.liu@epfl.ch>, Vasiliki Stergiopoulou <vasiliki.stergiopoulou@epfl.ch>, Jonathan Dong <jonathan.dong@epfl.ch>, Jonathan Chuah <jonathan.chuahwenjie@epfl.ch>, Daniel Sage <daniel.sage@epfl.ch>
Maintainer-email: Yan Liu <yan.liu@epfl.ch>, Vasiliki Stergiopoulou <vasiliki.stergiopoulou@epfl.ch>, Jonathan Dong <jonathan.dong@epfl.ch>
License: MIT License
Project-URL: Homepage, https://github.com/Biomedical-Imaging-Group/psf_generator
Project-URL: Documentation, https://psf-generator.readthedocs.io/
Project-URL: Repository, https://github.com/Biomedical-Imaging-Group/psf_generator.git
Project-URL: Bug Tracker, https://github.com/Biomedical-Imaging-Group/psf_generator/issues
Project-URL: Changelog, https://github.com/Biomedical-Imaging-Group/psf_generator/CHANGELOG.md
Keywords: point-spread-function,pytorch,deep learning,fluorescence microscopy,imaging,optical system,psf engineering,light propagation
Classifier: Development Status :: 4 - Beta
Classifier: Programming Language :: Python :: 3.8
Requires-Python: >=3.8
License-File: LICENSE
Requires-Dist: matplotlib>=3.6.1
Requires-Dist: numpy>=1.23.4
Requires-Dist: scipy>=1.9.1
Requires-Dist: torch>=2.0.0
Requires-Dist: zernikepy>=0.0.5
Requires-Dist: scikit-image
Dynamic: license-file
